{"data":{"1":{"dailyChange":-3.06,"weeklyChange":-1.46,"monthlyChange":0.22,"quarterChange":26.48,"halfChange":45.24,"yearlyChange":177.12,"ytdChange":34.13},"2":{"dailyChange":-2.85,"weeklyChange":2.55,"monthlyChange":10.9,"quarterChange":57.17,"halfChange":223.97,"yearlyChange":302.16,"ytdChange":39.25},"3":{"dailyChange":-2.3,"weeklyChange":0.76,"monthlyChange":-14.08,"quarterChange":29.35,"halfChange":42.35,"yearlyChange":140.18,"ytdChange":17.63},"4":{"dailyChange":1.43,"weeklyChange":4.28,"monthlyChange":-3.94,"quarterChange":5.57,"halfChange":25.28,"yearlyChange":15.64,"ytdChange":-2.45},"5":{"dailyChange":-4.11,"weeklyChange":-6.06,"monthlyChange":-17.13,"quarterChange":-15.45,"halfChange":53.27,"yearlyChange":91.71,"ytdChange":-0.73},"6":{"dailyChange":-1.27,"weeklyChange":12.27,"monthlyChange":19.61,"quarterChange":38.02,"halfChange":99.13,"yearlyChange":146.99,"ytdChange":22.3},"7":{"dailyChange":-0.75,"weeklyChange":1.87,"monthlyChange":4.58,"quarterChange":24.42,"halfChange":34.17,"yearlyChange":59.28,"ytdChange":15.52},"8":{"dailyChange":-1.63,"weeklyChange":0.84,"monthlyChange":-8.78,"quarterChange":-5.89,"halfChange":19.47,"yearlyChange":19.64,"ytdChange":-3.32},"9":{"dailyChange":-0.06,"weeklyChange":-0.64,"monthlyChange":-9.02,"quarterChange":-9.29,"halfChange":-7.9,"yearlyChange":4.96,"ytdChange":-5.47},"10":{"dailyChange":-0.24,"weeklyChange":-3.39,"monthlyChange":-14.84,"quarterChange":-15.94,"halfChange":-16.28,"yearlyChange":-2.21,"ytdChange":-12.39},"11":{"dailyChange":-0.86,"weeklyChange":3.59,"monthlyChange":-6.41,"quarterChange":-8.14,"halfChange":-5.19,"yearlyChange":21.31,"ytdChange":-4.05},"12":{"dailyChange":-0.82,"weeklyChange":-3.78,"monthlyChange":-11.56,"quarterChange":3.15,"halfChange":32.21,"yearlyChange":12.23,"ytdChange":-3.32},"13":{"dailyChange":-0.69,"weeklyChange":-1.6,"monthlyChange":-4.82,"quarterChange":10.87,"halfChange":45.56,"yearlyChange":48.41,"ytdChange":-0.66},"14":{"dailyChange":-2.8,"weeklyChange":-1.63,"monthlyChange":-30.37,"quarterChange":-27.04,"halfChange":-37,"yearlyChange":-3.55,"ytdChange":-20.23},"15":{"dailyChange":-2.03,"weeklyChange":-2.84,"monthlyChange":-2.78,"quarterChange":29.39,"halfChange":246.09,"yearlyChange":123.47,"ytdChange":-7.18},"16":{"dailyChange":2.54,"weeklyChange":5.95,"monthlyChange":-18.84,"quarterChange":-13.26,"halfChange":-11.74,"yearlyChange":8.68,"ytdChange":-16.02},"17":{"dailyChange":-0.89,"weeklyChange":-1.98,"monthlyChange":2.2,"quarterChange":9.49,"halfChange":33.24,"yearlyChange":24.5,"ytdChange":4.75}},"savedAt":1770814512589}