{"data":{"1":{"dailyChange":-0.02,"weeklyChange":-6.48,"monthlyChange":-12.25,"quarterChange":16.58,"halfChange":35.87,"yearlyChange":151.5,"ytdChange":22.47},"2":{"dailyChange":-0.67,"weeklyChange":4.08,"monthlyChange":23.51,"quarterChange":68.36,"halfChange":260.56,"yearlyChange":341.69,"ytdChange":51.29},"3":{"dailyChange":-0.17,"weeklyChange":-2.33,"monthlyChange":-17.95,"quarterChange":25.88,"halfChange":38.13,"yearlyChange":126.21,"ytdChange":13.66},"4":{"dailyChange":0,"weeklyChange":1,"monthlyChange":-3.59,"quarterChange":4.06,"halfChange":23.29,"yearlyChange":18.1,"ytdChange":-3.82},"5":{"dailyChange":-0.92,"weeklyChange":-9.42,"monthlyChange":-26.6,"quarterChange":-23.23,"halfChange":38.32,"yearlyChange":71.88,"ytdChange":-10.37},"6":{"dailyChange":-0.13,"weeklyChange":4.13,"monthlyChange":18.48,"quarterChange":38.02,"halfChange":97.88,"yearlyChange":153.99,"ytdChange":22.48},"7":{"dailyChange":-0.11,"weeklyChange":0.21,"monthlyChange":2.95,"quarterChange":23.78,"halfChange":33.19,"yearlyChange":55.94,"ytdChange":15.73},"8":{"dailyChange":-0.03,"weeklyChange":-10.17,"monthlyChange":-37.17,"quarterChange":-29.5,"halfChange":-10.29,"yearlyChange":55.36,"ytdChange":-27.65},"9":{"dailyChange":-0.09,"weeklyChange":-2.07,"monthlyChange":-10.76,"quarterChange":-9.25,"halfChange":-9.75,"yearlyChange":7.4,"ytdChange":-7.56},"10":{"dailyChange":-0.83,"weeklyChange":-0.93,"monthlyChange":-14.04,"quarterChange":-18.72,"halfChange":-18.9,"yearlyChange":-4.3,"ytdChange":-15},"11":{"dailyChange":0,"weeklyChange":-4.85,"monthlyChange":-13.85,"quarterChange":-12.82,"halfChange":-10.46,"yearlyChange":11.43,"ytdChange":-9.23},"12":{"dailyChange":0,"weeklyChange":-4.07,"monthlyChange":-15.62,"quarterChange":0.19,"halfChange":29.13,"yearlyChange":14.45,"ytdChange":-6.54},"13":{"dailyChange":0,"weeklyChange":-3.06,"monthlyChange":-7.82,"quarterChange":7.84,"halfChange":40.93,"yearlyChange":48.24,"ytdChange":-3.78},"14":{"dailyChange":-0.72,"weeklyChange":-3.46,"monthlyChange":-31.26,"quarterChange":-28,"halfChange":-39,"yearlyChange":-8.89,"ytdChange":-22.7},"15":{"dailyChange":0,"weeklyChange":-4.13,"monthlyChange":-6.27,"quarterChange":28.97,"halfChange":268.9,"yearlyChange":139.79,"ytdChange":-6.65},"16":{"dailyChange":-0.42,"weeklyChange":-4.89,"monthlyChange":-24.04,"quarterChange":-21.07,"halfChange":-19.63,"yearlyChange":-5.05,"ytdChange":-23.89},"17":{"dailyChange":-0.01,"weeklyChange":0.8,"monthlyChange":3.85,"quarterChange":13.03,"halfChange":37.03,"yearlyChange":29.03,"ytdChange":7.93}},"savedAt":1770993263624}